{"cameraMode":{"drawMode":0,"name":"Shaded","section":"Shading Mode"},"sceneLighting":false,"audioPlay":false,"sceneViewState":{"m_AlwaysRefresh":false,"showFog":true,"showSkybox":false,"showFlares":true,"showImageEffects":true,"showParticleSystems":true,"showVisualEffectGraphs":true,"m_FxEnabled":true},"in2DMode":false,"pivot":{"x":-6.592238903045654,"y":-0.16672968864440919,"z":-8.148160934448243},"rotation":{"x":-0.24684575200080872,"y":0.7205970883369446,"z":-0.3138059079647064,"w":-0.5668942928314209},"size":21.146318435668947,"orthographic":false}